{
  "project_info": {
    "project_number": "259524901583",
    "project_id": "testandroidapp-914bb",
    "storage_bucket": "testandroidapp-914bb.appspot.com"
  },
  "client": [
    {
      "client_info": {
        "mobilesdk_app_id": "1:259524901583:android:34128763208cb72f6915ba",
        "android_client_info": {
          "package_name": "com.kost4n.testandroidapp"
        }
      },
      "oauth_client": [
        {
          "client_id": "259524901583-72goiqlb627rpcf04vuhh3qn6u8kh9iq.apps.googleusercontent.com",
          "client_type": 3
        }
      ],
      "api_key": [
        {
          "current_key": "AIzaSyC1QIhhM1HmEf8JRRRiseNq4peiNeJ_dV8"
        }
      ],
      "services": {
        "appinvite_service": {
          "other_platform_oauth_client": [
            {
              "client_id": "259524901583-72goiqlb627rpcf04vuhh3qn6u8kh9iq.apps.googleusercontent.com",
              "client_type": 3
            }
          ]
        }
      }
    }
  ],
  "configuration_version": "1"
}